src/Readme.md
src/answer.txt
src/demo.py
openagi/__init__.py
openagi/actions/__init__.py
openagi/actions/base.py
openagi/actions/compressor.py
openagi/actions/console.py
openagi/actions/files.py
openagi/actions/formatter.py
openagi/actions/human_input.py
openagi/actions/obs_rag.py
openagi/actions/tools/__init__.py
openagi/actions/tools/arxiv_search.py
openagi/actions/tools/ddg_search.py
openagi/actions/tools/document_loader.py
openagi/actions/tools/exasearch.py
openagi/actions/tools/github_search_tool.py
openagi/actions/tools/google_search_tool.py
openagi/actions/tools/pubmed_tool.py
openagi/actions/tools/searchapi_search.py
openagi/actions/tools/serp_search.py
openagi/actions/tools/serper_search.py
openagi/actions/tools/tavilyqasearch.py
openagi/actions/tools/unstructured_io.py
openagi/actions/tools/webloader.py
openagi/actions/tools/yahoo_finance.py
openagi/actions/tools/youtubesearch.py
openagi/actions/utils.py
openagi/agent.py
openagi/cli.py
openagi/exception.py
openagi/llms/__init__.py
openagi/llms/azure.py
openagi/llms/base.py
openagi/llms/claude.py
openagi/llms/cohere.py
openagi/llms/gemini.py
openagi/llms/groq.py
openagi/llms/hf.py
openagi/llms/mistral.py
openagi/llms/ollama.py
openagi/llms/openai.py
openagi/llms/xai.py
openagi/memory/__init__.py
openagi/memory/base.py
openagi/memory/memory.py
openagi/memory/sessiondict.py
openagi/planner/LATS.py
openagi/planner/__init__.py
openagi/planner/base.py
openagi/planner/reflexion.py
openagi/planner/task_decomposer.py
openagi/prompts/__init__.py
openagi/prompts/base.py
openagi/prompts/constants.py
openagi/prompts/execution.py
openagi/prompts/ltm.py
openagi/prompts/summarizer.py
openagi/prompts/task_clarification.py
openagi/prompts/task_creator.py
openagi/prompts/worker_task_execution.py
openagi/storage/__init__.py
openagi/storage/base.py
openagi/storage/chroma.py
openagi/tasks/__init__.py
openagi/tasks/lists.py
openagi/tasks/task.py
openagi/utils/extraction.py
openagi/utils/helper.py
openagi/utils/llmTasks.py
openagi-0.2.9.8.1.dist-info/METADATA
openagi-0.2.9.8.1.dist-info/WHEEL
openagi-0.2.9.8.1.dist-info/entry_points.txt
openagi-0.2.9.8.1.dist-info/RECORD
