Metadata-Version: 2.1
Name: openagi
Version: 0.2.9.8.1
Summary: 
Author: AI Planet
Author-email: tech@aiplanet.com
Requires-Python: >=3.9,<3.12
Classifier: Programming Language :: Python :: 3
Classifier: Programming Language :: Python :: 3.9
Classifier: Programming Language :: Python :: 3.10
Classifier: Programming Language :: Python :: 3.11
Requires-Dist: azure-identity (>=1.15.0,<2.0.0)
Requires-Dist: chromadb (>=0.5.0,<0.6.0)
Requires-Dist: duckduckgo-search (>=6.1.0,<7.0.0)
Requires-Dist: faiss-cpu (>=1.8.0,<2.0.0)
Requires-Dist: fake-useragent (>=1.5.1,<2.0.0)
Requires-Dist: fastapi (>=0.110.0,<0.111.0)
Requires-Dist: google-api-python-client (>=2.121.0,<3.0.0)
Requires-Dist: google-auth-httplib2 (>=0.2.0,<0.3.0)
Requires-Dist: google-auth-oauthlib (>=1.2.0,<2.0.0)
Requires-Dist: google-search-results (>=2.4.2,<3.0.0)
Requires-Dist: langchain (>=0.1.9,<0.2.0)
Requires-Dist: langchain-community (>=0.0.21,<0.0.22)
Requires-Dist: langchain-core (>=0.1.27,<0.2.0)
Requires-Dist: langchain-exa (>=0.0.1,<0.0.2)
Requires-Dist: langchain-experimental (>=0.0.53,<0.0.54)
Requires-Dist: langchain-openai (>=0.0.6,<0.0.7)
Requires-Dist: langchain-text-splitters (>=0.0.1,<0.0.2)
Requires-Dist: langchainhub (>=0.1.15,<0.2.0)
Requires-Dist: numpy (>=1.26.4,<2.0.0)
Requires-Dist: ollama (>=0.1.7,<0.2.0)
Requires-Dist: pandas (>=2.2.2,<3.0.0)
Requires-Dist: protobuf (>=3.20.3,<4.0.0)
Requires-Dist: pygithub (>=2.3.0,<3.0.0)
Requires-Dist: pypdf (>=4.2.0,<5.0.0)
Requires-Dist: pytest (>=8.2.0,<9.0.0)
Requires-Dist: python-dotenv (>=1.0.1,<2.0.0)
Requires-Dist: python-multipart (>=0.0.9,<0.0.10)
Requires-Dist: spacy (==3.7.4)
Requires-Dist: spacytextblob (>=4.0.0,<5.0.0)
Requires-Dist: sumy (>=0.11.0,<0.12.0)
Requires-Dist: tavily-python (>=0.4.0,<0.5.0)
Requires-Dist: transformers (>=4.40.0,<5.0.0)
Requires-Dist: uvicorn (>=0.29.0,<0.30.0)
Requires-Dist: wikipedia (>=1.4.0,<2.0.0)
Requires-Dist: xorbits (>=0.7.2,<0.8.0)
Requires-Dist: yfinance (>=0.2.37,<0.3.0)
Requires-Dist: youtube-search (>=2.1.2,<3.0.0)
Requires-Dist: yt-dlp (>=2024.8.6,<2025.0.0)
